datalad_debian/__init__.py
datalad_debian/_version.py
datalad_debian/add_distribution.py
datalad_debian/bootstrap_builder.py
datalad_debian/build_package.py
datalad_debian/configure_builder.py
datalad_debian/new_distribution.py
datalad_debian/new_package.py
datalad_debian/new_reprepro_repository.py
datalad_debian/update_reprepro_repository.py
datalad_debian/utils.py
datalad_debian/resources/recipes/singularity-default
datalad_debian/tests/__init__.py
datalad_debian/tests/test_from_scratch.py
datalad_debian/tests/test_new_reprepro_repository.py
datalad_debian/tests/test_register.py
datalad_debian/tests/test_update_reprepro_repository.py
datalad_debian/tests/test_utils.py
datalad_debian-0.0.1.dist-info/LICENSE
datalad_debian-0.0.1.dist-info/METADATA
datalad_debian-0.0.1.dist-info/WHEEL
datalad_debian-0.0.1.dist-info/entry_points.txt
datalad_debian-0.0.1.dist-info/top_level.txt
datalad_debian-0.0.1.dist-info/RECORD
