Metadata-Version: 2.1
Name: datalad-debian
Version: 0.0.1
Summary: DataLad extension for working with Debian packages and package repositories
Home-page: https://github.com/psychoinformatics-de/datalad-debian
Author: The DataLad Team and Contributors
Author-email: team@datalad.org
License: MIT
Platform: UNKNOWN
Classifier: Programming Language :: Python
Classifier: License :: OSI Approved :: BSD License
Classifier: Programming Language :: Python :: 3
Requires-Python: >=3.7
License-File: LICENSE
Requires-Dist: datalad (>=0.17)
Requires-Dist: datalad-container
Requires-Dist: python-debian
Provides-Extra: devel
Requires-Dist: pytest ; extra == 'devel'
Requires-Dist: pytest-cov ; extra == 'devel'
Requires-Dist: coverage ; extra == 'devel'
